youtubeplayer/Lib.py
youtubeplayer/__init__.py
youtubeplayer/config.py
youtubeplayer/database.py
youtubeplayer/y2mate.py
youtubeplayer/youtube.py
YouTubePlayer-0.0.8.dist-info/LICENSE
YouTubePlayer-0.0.8.dist-info/METADATA
YouTubePlayer-0.0.8.dist-info/WHEEL
YouTubePlayer-0.0.8.dist-info/top_level.txt
YouTubePlayer-0.0.8.dist-info/RECORD
