Metadata-Version: 2.1
Name: YouTubePlayer
Version: 0.0.8
Summary: innovata-YouTubePlayer
Home-page: https://github.com/innovata/YouTubePlayer
Author: innovata sambong
Author-email: iinnovata@gmail.com
License: UNKNOWN
Platform: UNKNOWN
Classifier: Programming Language :: Python :: 3
Classifier: License :: OSI Approved :: MIT License
Classifier: Operating System :: OS Independent
Requires-Python: >=3.8
License-File: LICENSE
Requires-Dist: idebug
Requires-Dist: requests
Requires-Dist: beautifulsoup4
Requires-Dist: pandas
